syrics/__init__.py
syrics/api.py
syrics/cli.py
syrics/core.py
syrics/exceptions.py
syrics/totp.py
syrics-0.1.2.5.dist-info/licenses/LICENSE
syrics-0.1.2.5.dist-info/METADATA
syrics-0.1.2.5.dist-info/WHEEL
syrics-0.1.2.5.dist-info/entry_points.txt
syrics-0.1.2.5.dist-info/top_level.txt
syrics-0.1.2.5.dist-info/RECORD
