Metadata-Version: 2.4
Name: syrics
Version: 0.1.2.5
Summary: A command line tool to fetch lyrics from spotify and save it to lrc file. It can fetch both synced and unsynced lyrics from spotify. 
Home-page: https://github.com/akashrchandran/syrics
Author: Akash R Chandran
Author-email: chandranrakash@gmail.com
Classifier: Programming Language :: Python :: 3
Classifier: License :: OSI Approved :: GNU General Public License (GPL)
Classifier: Operating System :: OS Independent
Requires-Python: >=3.6
License-File: LICENSE
Requires-Dist: requests
Requires-Dist: spotipy
Requires-Dist: tqdm
Requires-Dist: tinytag
Dynamic: author
Dynamic: author-email
Dynamic: classifier
Dynamic: description
Dynamic: description-content-type
Dynamic: home-page
Dynamic: license-file
Dynamic: requires-dist
Dynamic: requires-python
Dynamic: summary
